aws_user_setup/__init__.py
aws_user_setup-0.1.dist-info/METADATA
aws_user_setup-0.1.dist-info/WHEEL
aws_user_setup-0.1.dist-info/top_level.txt
aws_user_setup-0.1.dist-info/RECORD
