Metadata-Version: 2.1
Name: aws-user-setup
Version: 0.1
Summary: Setup users defined in a yml file
Home-page: http://www.advantest.com
Author: Alexander von Renteln
Author-email: alexander.vonrenteln@advantest.com
License: MIT
Platform: UNKNOWN
